{
    "type": "object",
    "properties": {
        "username": {
            "required": false,
            "type": "string"
        },
        "startAt": {
            "required": false,
            "type": "integer",
            "format": "int32"
        },
        "maxResults": {
            "required": false,
            "type": "integer",
            "format": "int32"
        },
        "includeActive": {
            "required": false,
            "type": "boolean"
        },
        "includeInactive": {
            "required": false,
            "type": "boolean"
        }
    }
}